[
  {
    "id": "16",
    "name": "肉じゃが",
    "category": "和食",
    "isRecommended": true,
    "imageUrl": "/images/menu/no-image.jpg",
    "description": "大葉の風味が効いただし巻き卵",
    "tags": ["じゃがいも", "にんじん", "たまねぎ", "豚肉" ]
  },
  {
    "id": "1",
    "name": "ローストビーフ",
    "category": "洋食",
    "isRecommended": false,
    "imageUrl": "/images/menu/1.jpg",
    "description": "柔らかく仕上げた特製ローストビーフ",
    "tags": ["牛肉", "赤身肉", "にんにく", "ローズマリー"],
    "recipe": {
      "ingredients": [
        {"name": "牛もも肉", "amount": "300g"},
        {"name": "にんにく", "amount": "2片"}, 
        {"name": "ローズマリー", "amount": "適量"}
      ],
      "steps": ["肉を塩胡椒で下味", "低温でじっくり焼く"]
    }
  },
  {
    "id": "3",
    "name": "カプレーゼ",
    "category": "イタリアン",
    "isRecommended": true,
    "imageUrl": "/images/menu/3.jpg",
    "description": "モッツァレラチーズとトマトのサラダ",
    "tags": ["トマト", "モッツァレラ", "バジル", "オリーブオイル"]
  },
  {
    "id": "5",
    "name": "ゴルゴンゾーラリガトーニ",
    "category": "イタリアン",
    "isRecommended": false,
    "imageUrl": "/images/menu/5.jpg",
    "description": "濃厚なゴルゴンゾーラソースのパスタ",
    "tags": ["パスタ", "ゴルゴンゾーラ", "生クリーム", "くるみ"]
  },
  {
    "id": "8",
    "name": "サーモンクリームパスタ",
    "category": "イタリアン",
    "isRecommended": true,
    "imageUrl": "/images/menu/8.jpg",
    "description": "生クリームとサーモンのパスタ",
    "tags": ["パスタ", "サーモン", "生クリーム", "白ワイン"]
  },
  {
    "id": "6",
    "name": "天津チャーハン",
    "category": "中華",
    "isRecommended": false,
    "imageUrl": "/images/menu/6.jpg",
    "description": "カニ風味の天津風チャーハン",
    "tags": ["ご飯", "卵", "カニカマ", "長ねぎ"]
  },
  {
    "id": "10",
    "name": "魯肉飯（ルーローハン）",
    "category": "中華",
    "isRecommended": false,
    "imageUrl": "/images/menu/10.jpg",
    "description": "台湾風の煮込み豚肉ご飯",
    "tags": ["豚肉", "ご飯", "醤油", "八角"]
  },
  {
    "id": "2",
    "name": "ガパオライス",
    "category": "エスニック", 
    "isRecommended": true,
    "imageUrl": "/images/menu/2.jpg",
    "description": "タイ風バジル炒め",
    "tags": ["鶏肉", "バジル", "唐辛子", "卵"],
    "recipe": {
      "ingredients": [
        {"name": "鶏ひき肉", "amount": "200g"},
        {"name": "バジル", "amount": "10枚"},
        {"name": "卵", "amount": "1個"}
      ]
    }
  },
  {
    "id": "7",
    "name": "キムチチャーハン",
    "category": "中華",
    "isRecommended": false,
    "imageUrl": "/images/menu/7.jpg",
    "description": "ピリ辛キムチのチャーハン",
    "tags": ["ご飯", "キムチ", "豚肉", "ごま油"]
  },
  {
    "id": "11",
    "name": "カレー",
    "category": "エスニック",
    "isRecommended": false,
    "imageUrl": "/images/menu/no-image.jpg",
    "description": "じっくり煮込んだカレー",
    "tags": ["ご飯", "じゃがいも", "にんじん", "たまねぎ", "豚肉", "ごま油"]
  },
  {
    "id": "12",
    "name": "だし巻き卵",
    "category": "一品",
    "isRecommended": true,
    "imageUrl": "/images/menu/no-image.jpg",
    "description": "だしの風味が効いただし巻き卵",
    "tags": ["卵", "だし", "砂糖"]
  },
  {
    "id": "9",
    "name": "大葉のだし巻き卵",
    "category": "一品",
    "isRecommended": true,
    "imageUrl": "/images/menu/9.jpg",
    "description": "大葉の風味が効いただし巻き卵",
    "tags": ["卵", "大葉", "だし", "砂糖"]
  },
  {
    "id": "13",
    "name": "豚汁",
    "category": "和食",
    "isRecommended": true,
    "imageUrl": "/images/menu/no-image.jpg",
    "description": "",
    "tags": ["みそ", "大根", "豚肉", "ごぼう", "にんじん", "こんにゃく"]
  },
  {
    "id": "14",
    "name": "味噌汁",
    "category": "一品",
    "isRecommended": false,
    "imageUrl": "/images/menu/no-image.jpg",
    "description": "だしの風味が味噌汁",
    "tags": ["みそ", "だし", "豆腐"]
  },
  {
    "id": "15",
    "name": "モスチキン",
    "category": "その他",
    "isRecommended": true,
    "imageUrl": "/images/menu/no-image.jpg",
    "description": "",
    "tags": ["鶏肉", "揚げ物"]
  },
  {
    "id": "17",
    "name": "ペペロンチーノ",
    "category": "イタリアン",
    "isRecommended": true,
    "imageUrl": "/images/menu/no-image.jpg",
    "description": "",
    "tags": ["パスタ", "にんにく", "唐辛子", "オリーブオイル"]
  },
  {
    "id": "18",
    "name": "オートミールお好み焼き",
    "category": "和食",
    "isRecommended": true,
    "imageUrl": "/images/menu/no-image.jpg",
    "description": "",
    "tags": ["オートミール", "キャベツ"]
  },
  {
    "id": "21", 
    "name": "ポテトサラダ",
    "category": "一品",
    "isRecommended": true,
    "imageUrl": "/images/menu/4.jpg",
    "description": "クリーミーな洋風ポテトサラダ",
    "tags": ["じゃがいも", "マヨネーズ", "たまねぎ", "きゅうり", "ベーコン"]
  },
  {
    "id": "4", 
    "name": "ポテトサラダ（洋風）",
    "category": "一品",
    "isRecommended": true,
    "imageUrl": "/images/menu/4.jpg",
    "description": "クリーミーな洋風ポテトサラダ",
    "tags": ["じゃがいも", "マヨネーズ", "たまねぎ", "きゅうり"]
  },
  {
    "id": "19", 
    "name": "ポテトサラダ（おつまみ風）",
    "category": "一品",
    "isRecommended": false,
    "imageUrl": "/images/menu/no-image.jpg",
    "description": "",
    "tags": ["じゃがいも", "マヨネーズ", "たまねぎ", "にんにく", "ベーコン"]
  },
  {
    "id": "20", 
    "name": "ポテトサラダ（和風）",
    "category": "一品",
    "isRecommended": false,
    "imageUrl": "/images/menu/no-image.jpg",
    "description": "",
    "tags": ["じゃがいも", "マヨネーズ", "たまねぎ", "鰹節"]
  },
  {
    "id": "22",
    "name": "きのこクリームパスタ",
    "category": "イタリアン",
    "isRecommended": true,
    "imageUrl": "/images/menu/8.jpg",
    "description": "生クリームとサーモンのパスタ",
    "tags": ["パスタ", "舞茸", "マッシュルーム", "生クリーム", "白ワイン"]
  },
  {
    "id": "23", 
    "name": "アボカド刺身",
    "category": "一品",
    "isRecommended": false,
    "imageUrl": "/images/menu/no-image.jpg",
    "description": "",
    "tags": ["アボカド", "わさび"]
  },
  {
    "id": "24",
    "name": "ポテトフライ",
    "category": "一品",
    "isRecommended": true,
    "imageUrl": "/images/menu/no-image.jpg",
    "description": "業務スーパーのやつ",
    "tags": ["じゃがいも"]
  },
  {
    "id": "25", 
    "name": "ちくわの磯辺揚げ",
    "category": "一品",
    "isRecommended": false,
    "imageUrl": "/images/menu/no-image.jpg",
    "description": "",
    "tags": ["ちくわ"]
  }
]
